sokoban/__init__.py
sokoban/environment.py
sokoban/moving.py
sokoban/network.py
sokoban/policy.py
sokoban/processor.py
sokoban/sampler.py
sokoban/utils.py
sokoban/visualizer.py
sokoban_rl-0.1.2.dist-info/LICENSE
sokoban_rl-0.1.2.dist-info/METADATA
sokoban_rl-0.1.2.dist-info/WHEEL
sokoban_rl-0.1.2.dist-info/top_level.txt
sokoban_rl-0.1.2.dist-info/RECORD
